CHANGELOG.txt
LICENSE
MANIFEST.in
README.md
setup.py
maximal/__init__.py
maximal/layers.py
maximal/models.py
maximal/schedules.py
maximal.egg-info/PKG-INFO
maximal.egg-info/SOURCES.txt
maximal.egg-info/dependency_links.txt
maximal.egg-info/requires.txt
maximal.egg-info/top_level.txt
tests/test_layer_outputs.py
tests/test_save_and_load.py