Metadata-Version: 2.1
Name: maximal
Version: 1.2
Summary: TensorFlow-compatible Transformer layers and models.
Home-page: https://github.com/IvanBongiorni/maximal
Author: Ivan Bongiorni
Author-email: ivanbongiorni@protonmail.com
License: MIT
Classifier: Development Status :: 5 - Production/Stable
Classifier: Intended Audience :: Developers
Classifier: Intended Audience :: Science/Research
Classifier: Topic :: Scientific/Engineering
Classifier: License :: OSI Approved :: MIT License
Classifier: Programming Language :: Python :: 3
License-File: LICENSE
